pantomath_sdk/__init__.py
pantomath_sdk/sdk.py
pantomath_sdk/client/__init__.py
pantomath_sdk/client/pantomath_api_client.py
pantomath_sdk/enums/__init__.py
pantomath_sdk/enums/asset_path.py
pantomath_sdk/enums/data_volume_object_type.py
pantomath_sdk/enums/dataset_type.py
pantomath_sdk/enums/job_did_not_run_at_method.py
pantomath_sdk/enums/job_object_type.py
pantomath_sdk/enums/job_run_log_status.py
pantomath_sdk/enums/job_trigger_type.py
pantomath_sdk/enums/job_type.py
pantomath_sdk/enums/object_type.py
pantomath_sdk/enums/platform_types.py
pantomath_sdk/model/__init__.py
pantomath_sdk/model/asset_path/__init__.py
pantomath_sdk/model/asset_path/asset_path.py
pantomath_sdk/model/dataset/__init__.py
pantomath_sdk/model/dataset/adf_data_flow.py
pantomath_sdk/model/dataset/adf_dataset.py
pantomath_sdk/model/dataset/dataiku_dataset.py
pantomath_sdk/model/dataset/dataiku_model.py
pantomath_sdk/model/dataset/dataset.py
pantomath_sdk/model/dataset/ftp.py
pantomath_sdk/model/dataset/power_bi_dashboard.py
pantomath_sdk/model/dataset/power_bi_data_flow_entity.py
pantomath_sdk/model/dataset/power_bi_dataset.py
pantomath_sdk/model/dataset/power_bi_report.py
pantomath_sdk/model/dataset/s3_bucket.py
pantomath_sdk/model/dataset/sql_materialized_view.py
pantomath_sdk/model/dataset/sql_table.py
pantomath_sdk/model/dataset/sql_view.py
pantomath_sdk/model/dataset/tableau_datasource.py
pantomath_sdk/model/dataset/tableau_workbook.py
pantomath_sdk/model/job/__init__.py
pantomath_sdk/model/job/adf_activity.py
pantomath_sdk/model/job/adf_pipelines.py
pantomath_sdk/model/job/astro_dag.py
pantomath_sdk/model/job/astro_task.py
pantomath_sdk/model/job/aws_lambda.py
pantomath_sdk/model/job/control_m_folder.py
pantomath_sdk/model/job/control_m_job.py
pantomath_sdk/model/job/dataiku_project.py
pantomath_sdk/model/job/dataiku_recipe.py
pantomath_sdk/model/job/dbt_jobs.py
pantomath_sdk/model/job/dbt_model.py
pantomath_sdk/model/job/fivetran_connector.py
pantomath_sdk/model/job/job.py
pantomath_sdk-0.4.0.dist-info/METADATA
pantomath_sdk-0.4.0.dist-info/WHEEL
pantomath_sdk-0.4.0.dist-info/top_level.txt
pantomath_sdk-0.4.0.dist-info/RECORD
