Metadata-Version: 2.1
Name: pantomath_sdk
Version: 0.4.0
Summary: Send custom, realtime logs to Pantomath through the Pantomath Python SDK
Author-email: John Berberich <john.berberich@pantomath.com>, Matt Giovanetti <matt.giovanetti@pantomath.com>
Project-URL: Homepage, https://github.com/Pantomath-Dev/sdk-python
Project-URL: Issues, https://github.com/Pantomath-Dev/sdk-python/issues
Classifier: Programming Language :: Python :: 2.7
Classifier: Programming Language :: Python :: 3
Classifier: Programming Language :: Python :: 3.8
Classifier: License :: OSI Approved :: ISC License (ISCL)
Classifier: Operating System :: OS Independent
Requires-Python: >=2.7
Requires-Dist: aenum ==3.1.15
Requires-Dist: requests >=2.27.1
